{
  "schema": "urm.capability.lattice.v1",
  "capabilities": [
    "read_state",
    "run_analysis_check",
    "spawn_worker",
    "mutate_apply_patch",
    "approve_write",
    "manage_session_lifecycle"
  ],
  "actions": {
    "adeu.get_app_state": {
      "capability": "read_state",
      "requires_writes_allowed": false,
      "requires_approval": false
    },
    "adeu.list_templates": {
      "capability": "read_state",
      "requires_writes_allowed": false,
      "requires_approval": false
    },
    "adeu.read_evidence": {
      "capability": "read_state",
      "requires_writes_allowed": false,
      "requires_approval": false
    },
    "adeu.run_workflow": {
      "capability": "run_analysis_check",
      "requires_writes_allowed": false,
      "requires_approval": false
    },
    "paper.ingest_text": {
      "capability": "run_analysis_check",
      "requires_writes_allowed": false,
      "requires_approval": false
    },
    "paper.extract_abstract_candidate": {
      "capability": "run_analysis_check",
      "requires_writes_allowed": false,
      "requires_approval": false
    },
    "paper.check_constraints": {
      "capability": "run_analysis_check",
      "requires_writes_allowed": false,
      "requires_approval": false
    },
    "paper.emit_artifact": {
      "capability": "run_analysis_check",
      "requires_writes_allowed": false,
      "requires_approval": false
    },
    "digest.ingest_text": {
      "capability": "run_analysis_check",
      "requires_writes_allowed": false,
      "requires_approval": false
    },
    "digest.extract_digest_candidate": {
      "capability": "run_analysis_check",
      "requires_writes_allowed": false,
      "requires_approval": false
    },
    "digest.check_constraints": {
      "capability": "run_analysis_check",
      "requires_writes_allowed": false,
      "requires_approval": false
    },
    "digest.emit_artifact": {
      "capability": "run_analysis_check",
      "requires_writes_allowed": false,
      "requires_approval": false
    },
    "urm.spawn_worker": {
      "capability": "spawn_worker",
      "requires_writes_allowed": false,
      "requires_approval": false
    },
    "adeu.apply_patch": {
      "capability": "mutate_apply_patch",
      "requires_writes_allowed": true,
      "requires_approval": true
    },
    "urm.set_mode.disable_writes": {
      "capability": "manage_session_lifecycle",
      "requires_writes_allowed": false,
      "requires_approval": false
    },
    "urm.set_mode.enable_writes": {
      "capability": "approve_write",
      "requires_writes_allowed": false,
      "requires_approval": true
    },
    "urm.turn.steer": {
      "capability": "manage_session_lifecycle",
      "requires_writes_allowed": false,
      "requires_approval": false
    },
    "urm.agent.spawn": {
      "capability": "manage_session_lifecycle",
      "requires_writes_allowed": false,
      "requires_approval": false
    },
    "urm.agent.cancel": {
      "capability": "manage_session_lifecycle",
      "requires_writes_allowed": false,
      "requires_approval": false
    },
    "urm.connectors.snapshot.create": {
      "capability": "manage_session_lifecycle",
      "requires_writes_allowed": false,
      "requires_approval": false
    },
    "urm.connectors.snapshot.get": {
      "capability": "read_state",
      "requires_writes_allowed": false,
      "requires_approval": false
    }
  }
}
